README.md
setup.py
alphavideo/__init__.py
alphavideo.egg-info/PKG-INFO
alphavideo.egg-info/SOURCES.txt
alphavideo.egg-info/dependency_links.txt
alphavideo.egg-info/requires.txt
alphavideo.egg-info/top_level.txt
alphavideo/action/__init__.py
alphavideo/action/AlphAction/ActionDetector.py
alphavideo/action/AlphAction/IA_structure.py
alphavideo/action/AlphAction/SlowFast.py
alphavideo/action/AlphAction/__init__.py
alphavideo/action/AlphAction/config.py
alphavideo/action/AlphAction/head.py
alphavideo/action/AlphAction/utils/IA_helper.py
alphavideo/action/AlphAction/utils/__init__.py
alphavideo/action/AlphAction/utils/misc.py
alphavideo/action/AlphAction/utils/registry.py
alphavideo/action/AlphAction/utils/structures.py
alphavideo/base/__init__.py
alphavideo/base/fpn.py
alphavideo/base/resnet3d.py
alphavideo/csrc/__init__.py
alphavideo/csrc/ROIAlign3d/ROIAlign3d_cuda.cpp
alphavideo/csrc/ROIAlign3d/ROIAlign3d_kernel.cu
alphavideo/csrc/tube_nms_c/__init__.py
alphavideo/csrc/tube_nms_c/setup.py
alphavideo/csrc/tube_nms_c/src/nms_cuda.cpp
alphavideo/csrc/tube_nms_c/src/nms_kernel.cu
alphavideo/loss/__init__.py
alphavideo/loss/focal_loss.py
alphavideo/model/AlphAction.py
alphavideo/model/TubeTK.py
alphavideo/model/__init__.py
alphavideo/mot/__init__.py
alphavideo/mot/TubeTK/TubeTK.py
alphavideo/mot/TubeTK/__init__.py
alphavideo/mot/TubeTK/config.py
alphavideo/mot/TubeTK/head.py
alphavideo/mot/TubeTK/utils.py
alphavideo/utils/__init__.py
alphavideo/utils/load_url.py
alphavideo/utils/roi_align_3d.py
alphavideo/utils/tube_nms.py