Metadata-Version: 1.2
Name: alphavideo
Version: 0.1
Summary: video understanding models proposed by MVIG in SJTU.
Home-page: http://mvig.sjtu.edu.cn
Author: Bo Pang
Author-email: 
Maintainer: 
Maintainer-email: 
License: MIT
Platform: UNKNOWN
